.bumpversion.cfg
CHANGES.txt
LICENSE.txt
MANIFEST.in
README
README.md
__init__.py
setup.py
examples/__init__.py
examples/example1.ipynb
examples/example1.py
examples/example1.pyc
examples/tests_example1.py
examples/data/fixedCosts.csv
examples/data/meanFruitPerTree.csv
examples/data/meanRevenuePerFruit.csv
examples/data/numTrees.csv
examples/data/sdFruitPerTree.csv
examples/data/sdRevenuePerFruit.csv
examples/data/traysPerTree.csv
examples/data/varCostsPerFruit.csv
montepylib/__init__.py
montepylib/extend.py
montepylib/io.py
montepylib/manip.py
montepylib/sim.py
montepylib/utils.py
montepylib.egg-info/PKG-INFO
montepylib.egg-info/SOURCES.txt
montepylib.egg-info/dependency_links.txt
montepylib.egg-info/requires.txt
montepylib.egg-info/top_level.txt
montepylib/tests/__init__.py
montepylib/tests/test_io.py
montepylib/tests/test_manip.py
montepylib/tests/test_sim.py
montepylib/tests/test_utils.py
talks/README.md
talks/notebook.pdf
talks/talk.html
talks/talk.ipynb
talks/css/notebook.css
talks/css/talk.css
talks/data/cashflows.xlsx
talks/data/fixedCosts.csv
talks/data/fruitPerTree.csv
talks/data/fruitPerTree2.csv
talks/data/numTrees.csv
talks/data/revenuePerFruit.csv
talks/data/varCostsPerFruit.csv
talks/img/goal.png
talks/img/oneProfit.png
talks/img/rogoff.png
talks/img/shutterstock_182874488.jpg
talks/img/tornado.png
talks/img/whale.png
talks/shower/License.md
talks/shower/Readme.md
talks/shower/shower.min.js
talks/shower/themes/ribbon/License.md
talks/shower/themes/ribbon/Readme.md
talks/shower/themes/ribbon/index.html
talks/shower/themes/ribbon/fonts/PTMono.woff
talks/shower/themes/ribbon/fonts/PTSans.Bold.Italic.woff
talks/shower/themes/ribbon/fonts/PTSans.Bold.woff
talks/shower/themes/ribbon/fonts/PTSans.Italic.woff
talks/shower/themes/ribbon/fonts/PTSans.Narrow.Bold.woff
talks/shower/themes/ribbon/fonts/PTSans.woff
talks/shower/themes/ribbon/images/grid-16x10.svg
talks/shower/themes/ribbon/images/grid-4x3.svg
talks/shower/themes/ribbon/images/linen.png
talks/shower/themes/ribbon/images/linen@2x.png
talks/shower/themes/ribbon/images/ribbon.svg
talks/shower/themes/ribbon/styles/screen.css