Metadata-Version: 1.0
Name: montepylib
Version: 0.0.4
Summary: Tools and examples to analyse high-impact business decisions, and dodge many of the problems of using spreadsheets
Home-page: https://bitbucket.org/artstr/montepylib
Author: Arthur Street
Author-email: arthur@artana.com.au
License: BSD LICENSE
Keywords: business,cashflows,analysis,decision,spreadsheet,monte carlo,finance,corporate
Platform: UNKNOWN
